tfs_seon_client/__init__.py
tfs_seon_client/service/__init__.py
tfs_seon_client/service/abstract_service.py
tfs_seon_client/service/project_service.py
tfs_seon_client/service/team_member_service.py
tfs_seon_client/service/team_project_service.py
tfs_integration_seon_client-1.2.1.dist-info/METADATA
tfs_integration_seon_client-1.2.1.dist-info/WHEEL
tfs_integration_seon_client-1.2.1.dist-info/top_level.txt
tfs_integration_seon_client-1.2.1.dist-info/RECORD
